pollination/ladybug/__init__.py
pollination/ladybug/translate.py
pollination_ladybug-0.2.4.dist-info/LICENSE
pollination_ladybug-0.2.4.dist-info/METADATA
pollination_ladybug-0.2.4.dist-info/WHEEL
pollination_ladybug-0.2.4.dist-info/top_level.txt
pollination_ladybug-0.2.4.dist-info/RECORD
