Metadata-Version: 2.1
Name: pollination-ladybug
Version: 0.2.4
Summary: Ladybug core plugin for Pollination.
Home-page: https://github.com/pollination/ladybug
Author: ladybug-tools
Author-email: info@ladybug.tools
Maintainer: chris, ladybug-tools
Maintainer-email: chris@ladybug.tools, info@ladybug.tools
License: PolyForm Shield License 1.0.0, https://polyformproject.org/wp-content/uploads/2020/06/PolyForm-Shield-1.0.0.txt
Project-URL: icon, https://raw.githubusercontent.com/ladybug-tools/artwork/master/icons_bugs/grasshopper_tabs/Ladybug.png
Project-URL: docker, https://hub.docker.com/r/ladybugtools/ladybug
Keywords: ladybug,ladybug-tools,epw,wea,ddy
License-File: LICENSE
Requires-Dist: pollination-dsl (>=0.15.3)
Requires-Dist: ladybug-core (>=0.42.6)
